{
  "city": {
    "id": 4644585,
    "name": "Nashville",
    "country": "US",
    "coord": {
      "lon": -86.784439,
      "lat": 36.16589
    },
    "zoom": 4,
    "time": 1489494238,
    "main": {
      "temp": 274.69,
      "pressure": 1019,
      "temp_min": 273.15,
      "temp_max": 275.15,
      "humidity": 89
    },
    "wind": {
      "speed": 5.1,
      "deg": 310
    },
    "clouds": {
      "all": 90
    },
    "weather": [
      {
        "id": 804,
        "main": "Clouds",
        "description": "overcast clouds",
        "icon": "04n"
      }
    ]
  }
}
